ascendpbm_package/__init__.py
ascendpbm_package/api/__init__.py
ascendpbm_package/api/rxnorm.py
ascendpbm_package/email/__init__.py
ascendpbm_package/email/erroremailer.py
ascendpbm_package/parallel/__init__.py
ascendpbm_package/parallel/multiprocess.py
ascendpbm_package/parsers/__init__.py
ascendpbm_package/parsers/base.py
ascendpbm_package/parsers/eightthirtyfour.py
ascendpbm_package/parsers/json.py
ascendpbm_package/parsers/phone_numbers.py
ascendpbm_package/reports/__init__.py
ascendpbm_package/reports/sql.py
ascendpbm_package/reports/tables.py
ascendpbm_package/reports/web.py
ascendpbm_package/timing/__init__.py
ascendpbm_package/timing/datedelta.py
modules/__init__.py
modules/email/__init__.py
modules/email/erroremailer.py
modules/reports/__init__.py
modules/reports/tables.py
ascendpbm_package-0.0.2.16.dist-info/METADATA
ascendpbm_package-0.0.2.16.dist-info/WHEEL
ascendpbm_package-0.0.2.16.dist-info/top_level.txt
ascendpbm_package-0.0.2.16.dist-info/RECORD
