Metadata-Version: 2.1
Name: ascendpbm-package
Version: 0.0.2.16
Summary: Common methods for handling ascendpbm's IT needs.
Author: Ian Kapenga
Author-email: <ikapenga@optimedhp.com>
Maintainer-email: <l.dominick@ascendpbm.com>
Keywords: python,pbm,pharmacy,employer insurance,ascendpbm,business logic
Classifier: Development Status :: 3 - Alpha
Classifier: Intended Audience :: Other Audience
Classifier: Programming Language :: Python :: 3
Classifier: Operating System :: Microsoft :: Windows
Requires-Dist: pandas
Requires-Dist: datetime
Requires-Dist: O365
Requires-Dist: pyodbc
Requires-Dist: numpy
Requires-Dist: requests-ntlm
